openaiflow/__init__.py
openaiflow/file_parser.py
openaiflow/openaiflow.py
tests/__init__.py
tests/test_openaiflow.py
openaiflow-0.1.4a0.dist-info/LICENSE
openaiflow-0.1.4a0.dist-info/METADATA
openaiflow-0.1.4a0.dist-info/WHEEL
openaiflow-0.1.4a0.dist-info/top_level.txt
openaiflow-0.1.4a0.dist-info/RECORD
