Metadata-Version: 2.1
Name: openaiflow
Version: 0.1.4a0
Summary: A Python wrapper for OpenAI API interactions.
Home-page: https://github.com/ikotun-dev/openaiflow
Author: Ikotun Collins
Author-email: danlogan2003@gmail.com
Classifier: Development Status :: 3 - Alpha
Classifier: Intended Audience :: Developers
Classifier: License :: OSI Approved :: MIT License
Classifier: Programming Language :: Python :: 3
Requires-Python: >=3.7
License-File: LICENSE
Requires-Dist: annotated-types
Requires-Dist: anyio
Requires-Dist: certifi
Requires-Dist: charset-normalizer
Requires-Dist: distro
Requires-Dist: h11
Requires-Dist: httpcore
Requires-Dist: httpx
Requires-Dist: idna
Requires-Dist: jiter
Requires-Dist: openai
Requires-Dist: pydantic
Requires-Dist: pydantic-core
Requires-Dist: python-dotenv
Requires-Dist: requests
Requires-Dist: sniffio
Requires-Dist: tqdm
Requires-Dist: typing-extensions
Requires-Dist: urllib3
